pytest_approvaltests.py
pytest_approvaltests-0.2.4.dist-info/LICENSE
pytest_approvaltests-0.2.4.dist-info/METADATA
pytest_approvaltests-0.2.4.dist-info/WHEEL
pytest_approvaltests-0.2.4.dist-info/entry_points.txt
pytest_approvaltests-0.2.4.dist-info/top_level.txt
pytest_approvaltests-0.2.4.dist-info/RECORD
