Metadata-Version: 2.1
Name: pytest-approvaltests
Version: 0.2.4
Summary: A plugin to use approvaltests with pytest
Home-page: https://github.com/approvals/pytest-approvaltests
Author: Emily Bache
Author-email: emily@bacheconsulting.com
Maintainer: Emily Bache
Maintainer-email: emily@bacheconsulting.com
License: MIT
Platform: UNKNOWN
Classifier: Development Status :: 4 - Beta
Classifier: Framework :: Pytest
Classifier: Intended Audience :: Developers
Classifier: Topic :: Software Development :: Testing
Classifier: Programming Language :: Python
Classifier: Programming Language :: Python :: 3.6
Classifier: Programming Language :: Python :: 3.7
Classifier: Programming Language :: Python :: 3.8
Classifier: Programming Language :: Python :: Implementation :: CPython
Classifier: Programming Language :: Python :: Implementation :: PyPy
Classifier: Operating System :: OS Independent
Classifier: License :: OSI Approved :: MIT License
Requires-Python: >=3.6.1
License-File: LICENSE
